odoo/addons/stock_card_report/README.rst
odoo/addons/stock_card_report/__init__.py
odoo/addons/stock_card_report/__manifest__.py
odoo/addons/stock_card_report/data/paper_format.xml
odoo/addons/stock_card_report/data/report_data.xml
odoo/addons/stock_card_report/i18n/es.po
odoo/addons/stock_card_report/i18n/es_EC.po
odoo/addons/stock_card_report/i18n/stock_card_report.pot
odoo/addons/stock_card_report/readme/CONTRIBUTORS.rst
odoo/addons/stock_card_report/readme/DESCRIPTION.rst
odoo/addons/stock_card_report/readme/USAGE.rst
odoo/addons/stock_card_report/reports/__init__.py
odoo/addons/stock_card_report/reports/stock_card_report.py
odoo/addons/stock_card_report/reports/stock_card_report.xml
odoo/addons/stock_card_report/reports/stock_card_report_xlsx.py
odoo/addons/stock_card_report/static/description/icon.png
odoo/addons/stock_card_report/static/description/index.html
odoo/addons/stock_card_report/static/src/css/report.css
odoo/addons/stock_card_report/static/src/js/stock_card_report_backend.js
odoo/addons/stock_card_report/tests/__init__.py
odoo/addons/stock_card_report/tests/test_stock_card_report.py
odoo/addons/stock_card_report/wizard/__init__.py
odoo/addons/stock_card_report/wizard/stock_card_report_wizard.py
odoo/addons/stock_card_report/wizard/stock_card_report_wizard_view.xml
odoo13_addon_stock_card_report-13.0.1.0.1.dev9.dist-info/METADATA
odoo13_addon_stock_card_report-13.0.1.0.1.dev9.dist-info/WHEEL
odoo13_addon_stock_card_report-13.0.1.0.1.dev9.dist-info/top_level.txt
odoo13_addon_stock_card_report-13.0.1.0.1.dev9.dist-info/RECORD
