Metadata-Version: 2.1
Name: odoo13-addon-stock-card-report
Version: 13.0.1.0.1.dev9
Summary: Add stock card report on Inventory Reporting.
Home-page: https://github.com/OCA/stock-logistics-reporting
Author: Ecosoft, Odoo Community Association (OCA)
Author-email: support@odoo-community.org
License: AGPL-3
Platform: UNKNOWN
Classifier: Programming Language :: Python
Classifier: Framework :: Odoo
Classifier: Framework :: Odoo :: 13.0
Classifier: License :: OSI Approved :: GNU Affero General Public License v3
Requires-Python: >=3.5
Requires-Dist: odoo13-addon-date-range
Requires-Dist: odoo13-addon-report-xlsx-helper
Requires-Dist: odoo <13.1dev,>=13.0a
